setup.py
ali_domain_sdk/__init__.py
ali_domain_sdk/alidomainutils.py
ali_domain_sdk.egg-info/PKG-INFO
ali_domain_sdk.egg-info/SOURCES.txt
ali_domain_sdk.egg-info/dependency_links.txt
ali_domain_sdk.egg-info/not-zip-safe
ali_domain_sdk.egg-info/requires.txt
ali_domain_sdk.egg-info/top_level.txt