Metadata-Version: 1.1
Name: ali-domain-sdk
Version: 0.1
Summary: 阿里域名解析SDK
Home-page: https://github.com/xzzpig/AliDomainSDK
Author: Mg_P
Author-email: w2xzzpig@hotmail.com
License: GNU General Public License v3.0
Platform: UNKNOWN
Classifier: Development Status :: 3 - Alpha
Classifier: Intended Audience :: Developers
Classifier: Operating System :: OS Independent
Classifier: Programming Language :: Python
Requires: requests
